cachebox-5.2.1.dist-info/METADATA
cachebox-5.2.1.dist-info/WHEEL
cachebox-5.2.1.dist-info/licenses/LICENSE
cachebox/__init__.py
cachebox/_cachebox.py
cachebox/_core.cpython-314-darwin.so
cachebox/_core.pyi
cachebox/py.typed
cachebox/utils.py
cachebox-5.2.1.dist-info/RECORD
