Metadata-Version: 2.4
Name: cachebox
Version: 5.2.1
Classifier: Programming Language :: Python :: Implementation :: CPython
Classifier: Programming Language :: Python :: Implementation :: PyPy
Classifier: Programming Language :: Python :: 3
Classifier: Programming Language :: Python :: 3 :: Only
Classifier: Programming Language :: Python :: 3.9
Classifier: Programming Language :: Python :: 3.10
Classifier: Programming Language :: Python :: 3.11
Classifier: Programming Language :: Python :: 3.12
Classifier: Programming Language :: Python :: 3.13
Classifier: Programming Language :: Python :: 3.14
Classifier: Programming Language :: Python
Classifier: Programming Language :: Rust
Classifier: Intended Audience :: Developers
Classifier: License :: OSI Approved :: MIT License
Classifier: Operating System :: POSIX :: Linux
Classifier: Operating System :: Microsoft :: Windows
Classifier: Operating System :: MacOS
Classifier: Typing :: Typed
License-File: LICENSE
Summary: The fastest memoizing and caching Python library written in Rust
Keywords: caching,cached,cachebox,cache,in-memory-caching,memoizing
Home-Page: https://github.com/awolverp/cachebox
Author-email: awolverp <awolverp@gmail.com>
License: MIT
Requires-Python: >=3.9
Project-URL: Homepage, https://github.com/awolverp/cachebox
